cliplayer/__init__.py
cliplayer/cliplayer.py
cliplayer/config/__init__.py
cliplayer/config/cliplayer.cfg
cliplayer/config/key_mappings.cfg
cliplayer-0.1.4.dist-info/LICENSE
cliplayer-0.1.4.dist-info/METADATA
cliplayer-0.1.4.dist-info/WHEEL
cliplayer-0.1.4.dist-info/entry_points.txt
cliplayer-0.1.4.dist-info/top_level.txt
cliplayer-0.1.4.dist-info/RECORD
