Metadata-Version: 2.1
Name: cliplayer
Version: 0.1.4
Summary: The cliplayer helps to script shell based lectures and screencast tutorials
Home-page: https://github.com/howto-kubernetes-info/cliplayer
Author: Stephan Gitz
Author-email: pypi@systremix.de
Classifier: Programming Language :: Python :: 3
Classifier: License :: OSI Approved :: MIT License
Classifier: Operating System :: POSIX
Requires-Python: >=3.7
License-File: LICENSE
Requires-Dist: pexpect>=4.9.0
